hcom/__init__.py
hcom/__main__.py
hcom/api.py
hcom/cli.py
hcom/launcher.py
hcom/relay.py
hcom/shared.py
hcom/terminal.py
hcom/commands/__init__.py
hcom/commands/admin.py
hcom/commands/bundle.py
hcom/commands/config_cmd.py
hcom/commands/events.py
hcom/commands/hooks_cmd.py
hcom/commands/lifecycle.py
hcom/commands/messaging.py
hcom/commands/query.py
hcom/commands/relay.py
hcom/commands/reset.py
hcom/commands/shim.py
hcom/commands/transcript.py
hcom/commands/utils.py
hcom/core/__init__.py
hcom/core/bootstrap.py
hcom/core/bundles.py
hcom/core/config.py
hcom/core/context.py
hcom/core/db.py
hcom/core/detail_levels.py
hcom/core/device.py
hcom/core/filters.py
hcom/core/helpers.py
hcom/core/identity.py
hcom/core/instances.py
hcom/core/log.py
hcom/core/messages.py
hcom/core/ops.py
hcom/core/paths.py
hcom/core/runtime.py
hcom/core/timeouts.py
hcom/core/tool_utils.py
hcom/core/transcript.py
hcom/hooks/__init__.py
hcom/hooks/dispatcher.py
hcom/hooks/family.py
hcom/hooks/parent.py
hcom/hooks/settings.py
hcom/hooks/subagent.py
hcom/hooks/utils.py
hcom/pty/__init__.py
hcom/pty/claude.py
hcom/pty/codex.py
hcom/pty/gemini.py
hcom/pty/pty_common.py
hcom/pty/pty_handler.py
hcom/pty/pty_wrapper.py
hcom/pty/push_delivery.py
hcom/scripts/__init__.py
hcom/scripts/bundled/__init__.py
hcom/scripts/bundled/clone.py
hcom/scripts/bundled/confess.py
hcom/scripts/bundled/debate.py
hcom/scripts/bundled/ensemble.py
hcom/scripts/bundled/glue.py
hcom/scripts/bundled/watcher.py
hcom/tools/__init__.py
hcom/tools/args_common.py
hcom/tools/claude/__init__.py
hcom/tools/claude/args.py
hcom/tools/codex/__init__.py
hcom/tools/codex/args.py
hcom/tools/codex/hooks.py
hcom/tools/codex/preprocessing.py
hcom/tools/codex/settings.py
hcom/tools/codex/transcript.py
hcom/tools/gemini/__init__.py
hcom/tools/gemini/args.py
hcom/tools/gemini/hooks.py
hcom/tools/gemini/settings.py
hcom/ui/__init__.py
hcom/ui/colors.py
hcom/ui/input.py
hcom/ui/launch.py
hcom/ui/manage.py
hcom/ui/rendering.py
hcom/ui/tui.py
hcom-0.6.13.dist-info/METADATA
hcom-0.6.13.dist-info/WHEEL
hcom-0.6.13.dist-info/entry_points.txt
hcom-0.6.13.dist-info/top_level.txt
hcom-0.6.13.dist-info/RECORD
