Metadata-Version: 2.4
Name: hcom
Version: 0.6.13
Summary: Realtime messaging and context sharing for AI coding agents (Claude Code, Gemini CLI, Codex)
Author: aannoo
License-Expression: MIT
Project-URL: Homepage, https://github.com/aannoo/hcom
Project-URL: Repository, https://github.com/aannoo/hcom
Project-URL: Issues, https://github.com/aannoo/hcom/issues
Project-URL: Documentation, https://github.com/aannoo/hcom#readme
Keywords: claude,claude-code,gemini,codex,hooks,agents,cli,multi-agent,orchestration,terminal
Classifier: Development Status :: 4 - Beta
Classifier: Environment :: Console
Classifier: Intended Audience :: Developers
Classifier: Operating System :: OS Independent
Classifier: Operating System :: MacOS
Classifier: Operating System :: Microsoft :: Windows
Classifier: Operating System :: POSIX :: Linux
Classifier: Programming Language :: Python :: 3
Classifier: Programming Language :: Python :: 3 :: Only
Classifier: Topic :: Communications :: Chat
Classifier: Topic :: Software Development
Classifier: Topic :: System :: Monitoring
Classifier: Topic :: Terminals
Requires-Python: >=3.10
Requires-Dist: ptyprocess>=0.7.0
Requires-Dist: pyte>=0.8.2
